AAC2M4P2/AAC2M4P2.v
module RAM128x32
#(
  parameter Data_width = 32,  //# of bits in word
            Addr_width = 7  // # of address bits
  )
  (  //ports
    input wire clk,
    input wire we,
    input wire [(Addr_width-1):0] address,
    input wire [(Data_width-1):0] d,
    output wire [(Data_width-1):0] q
  );

  reg [Data_width - 1: 0] temp;
  reg [Data_width - 1: 0] ram [(Addr_width-1):0];

  assign q = we ? {Data_width{1'bz}} : ram[address];

  always @(posedge clk) begin
    if (we)
      // $display("%d", address);
      ram[address] <= d;
  end

  always @(posedge clk) begin
    if (!we)
      // $display("%d", address);
      temp <= ram[address];
  end
endmodule

AAC2M4P2/AAC2M4P2_tb.v
`timescale 1 ns/10 ps
`include "AAC2M4P2.v"
module RAM128x32_tb();

  parameter Data_width = 32;  //# of bits in word
  parameter Addr_width = 7;  // # of address bits

  reg clk = 0;
  reg we;
  reg [(Addr_width-1):0] address;
  reg [(Data_width-1):0] d;
  wire [(Data_width-1):0] q;

  RAM128x32 #(
      .Data_width(Data_width),
      .Addr_width(Addr_width)
    )
    ram
    (
      .clk(clk),
      .we(we),
      .address(address),
      .d(d),
      .q(q)
    );


  initial begin
    clk = 1'b0;
    forever #2 clk = ~clk;
  end

  initial begin
    $dumpfile("RAM128x32_tb.vcd");
    $dumpvars(0, RAM128x32_tb);
    
    we = 1;
    for(integer i = 0; i < {Addr_width{1'b1}}; i++) begin
      d <= i << 8;
      address <= i; #10;
      $display("WRITE: %d %d", address, d);
    end

    we = 0; #10;
    for(integer j = 0; j < {Addr_width{1'b1}}; j++) begin
      address <= j; #10;
      $display("READ:  %d %d", address, q);
    end

    we = 1;
    d <= 23456;
    address <= 34; #20;
    $display("WRITE: %d %d", address, q);
    we = 0; #20;
    $display("READ:  %d %d", address, q);

    $display("Howdy");
    $finish;
  end
endmodule

AAC2M4P2/RAM128x32_tb.vcd
$date
	Sun Mar 27 20:55:56 2022
$end
$version
	Icarus Verilog
$end
$timescale
	10ps
$end
$scope module RAM128x32_tb $end
$var wire 32 ! q [31:0] $end
$var reg 7 " address [6:0] $end
$var reg 1 # clk $end
$var reg 32 $ d [31:0] $end
$var reg 1 % we $end
$scope module ram $end
$var wire 7 & address [6:0] $end
$var wire 1 # clk $end
$var wire 32 ' d [31:0] $end
$var wire 1 % we $end
$var wire 32 ( q [31:0] $end
$var reg 32 ) temp [31:0] $end
$upscope $end
$scope begin $ivl_for_loop0 $end
$var integer 32 * i [31:0] $end
$upscope $end
$scope begin $ivl_for_loop1 $end
$var integer 32 + j [31:0] $end
$upscope $end
$upscope $end
$enddefinitions $end
#0
$dumpvars
bx +
b0 *
bx )
bz (
b0 '
b0 &
1%
b0 $
0#
b0 "
bz !
$end
#200
1#
#400
0#
#600
1#
#800
0#
#1000
b1 "
b1 &
b100000000 $
b100000000 '
1#
b1 *
#1200
0#
#1400
1#
#1600
0#
#1800
1#
#2000
b10 "
b10 &
b1000000000 $
b1000000000 '
0#
b10 *
#2200
1#
#2400
0#
#2600
1#
#2800
0#
#3000
b11 "
b11 &
b1100000000 $
b1100000000 '
1#
b11 *
#3200
0#
#3400
1#
#3600
0#
#3800
1#
#4000
b100 "
b100 &
b10000000000 $
b10000000000 '
0#
b100 *
#4200
1#
#4400
0#
#4600
1#
#4800
0#
#5000
b101 "
b101 &
b10100000000 $
b10100000000 '
1#
b101 *
#5200
0#
#5400
1#
#5600
0#
#5800
1#
#6000
b110 "
b110 &
b11000000000 $
b11000000000 '
0#
b110 *
#6200
1#
#6400
0#
#6600
1#
#6800
0#
#7000
b111 "
b111 &
b11100000000 $
b11100000000 '
1#
b111 *
#7200
0#
#7400
1#
#7600
0#
#7800
1#
#8000
b1000 "
b1000 &
b100000000000 $
b100000000000 '
0#
b1000 *
#8200
1#
#8400
0#
#8600
1#
#8800
0#
#9000
b1001 "
b1001 &
b100100000000 $
b100100000000 '
1#
b1001 *
#9200
0#
#9400
1#
#9600
0#
#9800
1#
#10000
b1010 "
b1010 &
b101000000000 $
b101000000000 '
0#
b1010 *
#10200
1#
#10400
0#
#10600
1#
#10800
0#
#11000
b1011 "
b1011 &
b101100000000 $
b101100000000 '
1#
b1011 *
#11200
0#
#11400
1#
#11600
0#
#11800
1#
#12000
b1100 "
b1100 &
b110000000000 $
b110000000000 '
0#
b1100 *
#12200
1#
#12400
0#
#12600
1#
#12800
0#
#13000
b1101 "
b1101 &
b110100000000 $
b110100000000 '
1#
b1101 *
#13200
0#
#13400
1#
#13600
0#
#13800
1#
#14000
b1110 "
b1110 &
b111000000000 $
b111000000000 '
0#
b1110 *
#14200
1#
#14400
0#
#14600
1#
#14800
0#
#15000
b1111 "
b1111 &
b111100000000 $
b111100000000 '
1#
b1111 *
#15200
0#
#15400
1#
#15600
0#
#15800
1#
#16000
b10000 "
b10000 &
b1000000000000 $
b1000000000000 '
0#
b10000 *
#16200
1#
#16400
0#
#16600
1#
#16800
0#
#17000
b10001 "
b10001 &
b1000100000000 $
b1000100000000 '
1#
b10001 *
#17200
0#
#17400
1#
#17600
0#
#17800
1#
#18000
b10010 "
b10010 &
b1001000000000 $
b1001000000000 '
0#
b10010 *
#18200
1#
#18400
0#
#18600
1#
#18800
0#
#19000
b10011 "
b10011 &
b1001100000000 $
b1001100000000 '
1#
b10011 *
#19200
0#
#19400
1#
#19600
0#
#19800
1#
#20000
b10100 "
b10100 &
b1010000000000 $
b1010000000000 '
0#
b10100 *
#20200
1#
#20400
0#
#20600
1#
#20800
0#
#21000
b10101 "
b10101 &
b1010100000000 $
b1010100000000 '
1#
b10101 *
#21200
0#
#21400
1#
#21600
0#
#21800
1#
#22000
b10110 "
b10110 &
b1011000000000 $
b1011000000000 '
0#
b10110 *
#22200
1#
#22400
0#
#22600
1#
#22800
0#
#23000
b10111 "
b10111 &
b1011100000000 $
b1011100000000 '
1#
b10111 *
#23200
0#
#23400
1#
#23600
0#
#23800
1#
#24000
b11000 "
b11000 &
b1100000000000 $
b1100000000000 '
0#
b11000 *
#24200
1#
#24400
0#
#24600
1#
#24800
0#
#25000
b11001 "
b11001 &
b1100100000000 $
b1100100000000 '
1#
b11001 *
#25200
0#
#25400
1#
#25600
0#
#25800
1#
#26000
b11010 "
b11010 &
b1101000000000 $
b1101000000000 '
0#
b11010 *
#26200
1#
#26400
0#
#26600
1#
#26800
0#
#27000
b11011 "
b11011 &
b1101100000000 $
b1101100000000 '
1#
b11011 *
#27200
0#
#27400
1#
#27600
0#
#27800
1#
#28000
b11100 "
b11100 &
b1110000000000 $
b1110000000000 '
0#
b11100 *
#28200
1#
#28400
0#
#28600
1#
#28800
0#
#29000
b11101 "
b11101 &
b1110100000000 $
b1110100000000 '
1#
b11101 *
#29200
0#
#29400
1#
#29600
0#
#29800
1#
#30000
b11110 "
b11110 &
b1111000000000 $
b1111000000000 '
0#
b11110 *
#30200
1#
#30400
0#
#30600
1#
#30800
0#
#31000
b11111 "
b11111 &
b1111100000000 $
b1111100000000 '
1#
b11111 *
#31200
0#
#31400
1#
#31600
0#
#31800
1#
#32000
b100000 "
b100000 &
b10000000000000 $
b10000000000000 '
0#
b100000 *
#32200
1#
#32400
0#
#32600
1#
#32800
0#
#33000
b100001 "
b100001 &
b10000100000000 $
b10000100000000 '
1#
b100001 *
#33200
0#
#33400
1#
#33600
0#
#33800
1#
#34000
b100010 "
b100010 &
b10001000000000 $
b10001000000000 '
0#
b100010 *
#34200
1#
#34400
0#
#34600
1#
#34800
0#
#35000
b100011 "
b100011 &
b10001100000000 $
b10001100000000 '
1#
b100011 *
#35200
0#
#35400
1#
#35600
0#
#35800
1#
#36000
b100100 "
b100100 &
b10010000000000 $
b10010000000000 '
0#
b100100 *
#36200
1#
#36400
0#
#36600
1#
#36800
0#
#37000
b100101 "
b100101 &
b10010100000000 $
b10010100000000 '
1#
b100101 *
#37200
0#
#37400
1#
#37600
0#
#37800
1#
#38000
b100110 "
b100110 &
b10011000000000 $
b10011000000000 '
0#
b100110 *
#38200
1#
#38400
0#
#38600
1#
#38800
0#
#39000
b100111 "
b100111 &
b10011100000000 $
b10011100000000 '
1#
b100111 *
#39200
0#
#39400
1#
#39600
0#
#39800
1#
#40000
b101000 "
b101000 &
b10100000000000 $
b10100000000000 '
0#
b101000 *
#40200
1#
#40400
0#
#40600
1#
#40800
0#
#41000
b101001 "
b101001 &
b10100100000000 $
b10100100000000 '
1#
b101001 *
#41200
0#
#41400
1#
#41600
0#
#41800
1#
#42000
b101010 "
b101010 &
b10101000000000 $
b10101000000000 '
0#
b101010 *
#42200
1#
#42400
0#
#42600
1#
#42800
0#
#43000
b101011 "
b101011 &
b10101100000000 $
b10101100000000 '
1#
b101011 *
#43200
0#
#43400
1#
#43600
0#
#43800
1#
#44000
b101100 "
b101100 &
b10110000000000 $
b10110000000000 '
0#
b101100 *
#44200
1#
#44400
0#
#44600
1#
#44800
0#
#45000
b101101 "
b101101 &
b10110100000000 $
b10110100000000 '
1#
b101101 *
#45200
0#
#45400
1#
#45600
0#
#45800
1#
#46000
b101110 "
b101110 &
b10111000000000 $
b10111000000000 '
0#
b101110 *
#46200
1#
#46400
0#
#46600
1#
#46800
0#
#47000
b101111 "
b101111 &
b10111100000000 $
b10111100000000 '
1#
b101111 *
#47200
0#
#47400
1#
#47600
0#
#47800
1#
#48000
b110000 "
b110000 &
b11000000000000 $
b11000000000000 '
0#
b110000 *
#48200
1#
#48400
0#
#48600
1#
#48800
0#
#49000
b110001 "
b110001 &
b11000100000000 $
b11000100000000 '
1#
b110001 *
#49200
0#
#49400
1#
#49600
0#
#49800
1#
#50000
b110010 "
b110010 &
b11001000000000 $
b11001000000000 '
0#
b110010 *
#50200
1#
#50400
0#
#50600
1#
#50800
0#
#51000
b110011 "
b110011 &
b11001100000000 $
b11001100000000 '
1#
b110011 *
#51200
0#
#51400
1#
#51600
0#
#51800
1#
#52000
b110100 "
b110100 &
b11010000000000 $
b11010000000000 '
0#
b110100 *
#52200
1#
#52400
0#
#52600
1#
#52800
0#
#53000
b110101 "
b110101 &
b11010100000000 $
b11010100000000 '
1#
b110101 *
#53200
0#
#53400
1#
#53600
0#
#53800
1#
#54000
b110110 "
b110110 &
b11011000000000 $
b11011000000000 '
0#
b110110 *
#54200
1#
#54400
0#
#54600
1#
#54800
0#
#55000
b110111 "
b110111 &
b11011100000000 $
b11011100000000 '
1#
b110111 *
#55200
0#
#55400
1#
#55600
0#
#55800
1#
#56000
b111000 "
b111000 &
b11100000000000 $
b11100000000000 '
0#
b111000 *
#56200
1#
#56400
0#
#56600
1#
#56800
0#
#57000
b111001 "
b111001 &
b11100100000000 $
b11100100000000 '
1#
b111001 *
#57200
0#
#57400
1#
#57600
0#
#57800
1#
#58000
b111010 "
b111010 &
b11101000000000 $
b11101000000000 '
0#
b111010 *
#58200
1#
#58400
0#
#58600
1#
#58800
0#
#59000
b111011 "
b111011 &
b11101100000000 $
b11101100000000 '
1#
b111011 *
#59200
0#
#59400
1#
#59600
0#
#59800
1#
#60000
b111100 "
b111100 &
b11110000000000 $
b11110000000000 '
0#
b111100 *
#60200
1#
#60400
0#
#60600
1#
#60800
0#
#61000
b111101 "
b111101 &
b11110100000000 $
b11110100000000 '
1#
b111101 *
#61200
0#
#61400
1#
#61600
0#
#61800
1#
#62000
b111110 "
b111110 &
b11111000000000 $
b11111000000000 '
0#
b111110 *
#62200
1#
#62400
0#
#62600
1#
#62800
0#
#63000
b111111 "
b111111 &
b11111100000000 $
b11111100000000 '
1#
b111111 *
#63200
0#
#63400
1#
#63600
0#
#63800
1#
#64000
b1000000 "
b1000000 &
b100000000000000 $
b100000000000000 '
0#
b1000000 *
#64200
1#
#64400
0#
#64600
1#
#64800
0#
#65000
b1000001 "
b1000001 &
b100000100000000 $
b100000100000000 '
1#
b1000001 *
#65200
0#
#65400
1#
#65600
0#
#65800
1#
#66000
b1000010 "
b1000010 &
b100001000000000 $
b100001000000000 '
0#
b1000010 *
#66200
1#
#66400
0#
#66600
1#
#66800
0#
#67000
b1000011 "
b1000011 &
b100001100000000 $
b100001100000000 '
1#
b1000011 *
#67200
0#
#67400
1#
#67600
0#
#67800
1#
#68000
b1000100 "
b1000100 &
b100010000000000 $
b100010000000000 '
0#
b1000100 *
#68200
1#
#68400
0#
#68600
1#
#68800
0#
#69000
b1000101 "
b1000101 &
b100010100000000 $
b100010100000000 '
1#
b1000101 *
#69200
0#
#69400
1#
#69600
0#
#69800
1#
#70000
b1000110 "
b1000110 &
b100011000000000 $
b100011000000000 '
0#
b1000110 *
#70200
1#
#70400
0#
#70600
1#
#70800
0#
#71000
b1000111 "
b1000111 &
b100011100000000 $
b100011100000000 '
1#
b1000111 *
#71200
0#
#71400
1#
#71600
0#
#71800
1#
#72000
b1001000 "
b1001000 &
b100100000000000 $
b100100000000000 '
0#
b1001000 *
#72200
1#
#72400
0#
#72600
1#
#72800
0#
#73000
b1001001 "
b1001001 &
b100100100000000 $
b100100100000000 '
1#
b1001001 *
#73200
0#
#73400
1#
#73600
0#
#73800
1#
#74000
b1001010 "
b1001010 &
b100101000000000 $
b100101000000000 '
0#
b1001010 *
#74200
1#
#74400
0#
#74600
1#
#74800
0#
#75000
b1001011 "
b1001011 &
b100101100000000 $
b100101100000000 '
1#
b1001011 *
#75200
0#
#75400
1#
#75600
0#
#75800
1#
#76000
b1001100 "
b1001100 &
b100110000000000 $
b100110000000000 '
0#
b1001100 *
#76200
1#
#76400
0#
#76600
1#
#76800
0#
#77000
b1001101 "
b1001101 &
b100110100000000 $
b100110100000000 '
1#
b1001101 *
#77200
0#
#77400
1#
#77600
0#
#77800
1#
#78000
b1001110 "
b1001110 &
b100111000000000 $
b100111000000000 '
0#
b1001110 *
#78200
1#
#78400
0#
#78600
1#
#78800
0#
#79000
b1001111 "
b1001111 &
b100111100000000 $
b100111100000000 '
1#
b1001111 *
#79200
0#
#79400
1#
#79600
0#
#79800
1#
#80000
b1010000 "
b1010000 &
b101000000000000 $
b101000000000000 '
0#
b1010000 *
#80200
1#
#80400
0#
#80600
1#
#80800
0#
#81000
b1010001 "
b1010001 &
b101000100000000 $
b101000100000000 '
1#
b1010001 *
#81200
0#
#81400
1#
#81600
0#
#81800
1#
#82000
b1010010 "
b1010010 &
b101001000000000 $
b101001000000000 '
0#
b1010010 *
#82200
1#
#82400
0#
#82600
1#
#82800
0#
#83000
b1010011 "
b1010011 &
b101001100000000 $
b101001100000000 '
1#
b1010011 *
#83200
0#
#83400
1#
#83600
0#
#83800
1#
#84000
b1010100 "
b1010100 &
b101010000000000 $
b101010000000000 '
0#
b1010100 *
#84200
1#
#84400
0#
#84600
1#
#84800
0#
#85000
b1010101 "
b1010101 &
b101010100000000 $
b101010100000000 '
1#
b1010101 *
#85200
0#
#85400
1#
#85600
0#
#85800
1#
#86000
b1010110 "
b1010110 &
b101011000000000 $
b101011000000000 '
0#
b1010110 *
#86200
1#
#86400
0#
#86600
1#
#86800
0#
#87000
b1010111 "
b1010111 &
b101011100000000 $
b101011100000000 '
1#
b1010111 *
#87200
0#
#87400
1#
#87600
0#
#87800
1#
#88000
b1011000 "
b1011000 &
b101100000000000 $
b101100000000000 '
0#
b1011000 *
#88200
1#
#88400
0#
#88600
1#
#88800
0#
#89000
b1011001 "
b1011001 &
b101100100000000 $
b101100100000000 '
1#
b1011001 *
#89200
0#
#89400
1#
#89600
0#
#89800
1#
#90000
b1011010 "
b1011010 &
b101101000000000 $
b101101000000000 '
0#
b1011010 *
#90200
1#
#90400
0#
#90600
1#
#90800
0#
#91000
b1011011 "
b1011011 &
b101101100000000 $
b101101100000000 '
1#
b1011011 *
#91200
0#
#91400
1#
#91600
0#
#91800
1#
#92000
b1011100 "
b1011100 &
b101110000000000 $
b101110000000000 '
0#
b1011100 *
#92200
1#
#92400
0#
#92600
1#
#92800
0#
#93000
b1011101 "
b1011101 &
b101110100000000 $
b101110100000000 '
1#
b1011101 *
#93200
0#
#93400
1#
#93600
0#
#93800
1#
#94000
b1011110 "
b1011110 &
b101111000000000 $
b101111000000000 '
0#
b1011110 *
#94200
1#
#94400
0#
#94600
1#
#94800
0#
#95000
b1011111 "
b1011111 &
b101111100000000 $
b101111100000000 '
1#
b1011111 *
#95200
0#
#95400
1#
#95600
0#
#95800
1#
#96000
b1100000 "
b1100000 &
b110000000000000 $
b110000000000000 '
0#
b1100000 *
#96200
1#
#96400
0#
#96600
1#
#96800
0#
#97000
b1100001 "
b1100001 &
b110000100000000 $
b110000100000000 '
1#
b1100001 *
#97200
0#
#97400
1#
#97600
0#
#97800
1#
#98000
b1100010 "
b1100010 &
b110001000000000 $
b110001000000000 '
0#
b1100010 *
#98200
1#
#98400
0#
#98600
1#
#98800
0#
#99000
b1100011 "
b1100011 &
b110001100000000 $
b110001100000000 '
1#
b1100011 *
#99200
0#
#99400
1#
#99600
0#
#99800
1#
#100000
b1100100 "
b1100100 &
b110010000000000 $
b110010000000000 '
0#
b1100100 *
#100200
1#
#100400
0#
#100600
1#
#100800
0#
#101000
b1100101 "
b1100101 &
b110010100000000 $
b110010100000000 '
1#
b1100101 *
#101200
0#
#101400
1#
#101600
0#
#101800
1#
#102000
b1100110 "
b1100110 &
b110011000000000 $
b110011000000000 '
0#
b1100110 *
#102200
1#
#102400
0#
#102600
1#
#102800
0#
#103000
b1100111 "
b1100111 &
b110011100000000 $
b110011100000000 '
1#
b1100111 *
#103200
0#
#103400
1#
#103600
0#
#103800
1#
#104000
b1101000 "
b1101000 &
b110100000000000 $
b110100000000000 '
0#
b1101000 *
#104200
1#
#104400
0#
#104600
1#
#104800
0#
#105000
b1101001 "
b1101001 &
b110100100000000 $
b110100100000000 '
1#
b1101001 *
#105200
0#
#105400
1#
#105600
0#
#105800
1#
#106000
b1101010 "
b1101010 &
b110101000000000 $
b110101000000000 '
0#
b1101010 *
#106200
1#
#106400
0#
#106600
1#
#106800
0#
#107000
b1101011 "
b1101011 &
b110101100000000 $
b110101100000000 '
1#
b1101011 *
#107200
0#
#107400
1#
#107600
0#
#107800
1#
#108000
b1101100 "
b1101100 &
b110110000000000 $
b110110000000000 '
0#
b1101100 *
#108200
1#
#108400
0#
#108600
1#
#108800
0#
#109000
b1101101 "
b1101101 &
b110110100000000 $
b110110100000000 '
1#
b1101101 *
#109200
0#
#109400
1#
#109600
0#
#109800
1#
#110000
b1101110 "
b1101110 &
b110111000000000 $
b110111000000000 '
0#
b1101110 *
#110200
1#
#110400
0#
#110600
1#
#110800
0#
#111000
b1101111 "
b1101111 &
b110111100000000 $
b110111100000000 '
1#
b1101111 *
#111200
0#
#111400
1#
#111600
0#
#111800
1#
#112000
b1110000 "
b1110000 &
b111000000000000 $
b111000000000000 '
0#
b1110000 *
#112200
1#
#112400
0#
#112600
1#
#112800
0#
#113000
b1110001 "
b1110001 &
b111000100000000 $
b111000100000000 '
1#
b1110001 *
#113200
0#
#113400
1#
#113600
0#
#113800
1#
#114000
b1110010 "
b1110010 &
b111001000000000 $
b111001000000000 '
0#
b1110010 *
#114200
1#
#114400
0#
#114600
1#
#114800
0#
#115000
b1110011 "
b1110011 &
b111001100000000 $
b111001100000000 '
1#
b1110011 *
#115200
0#
#115400
1#
#115600
0#
#115800
1#
#116000
b1110100 "
b1110100 &
b111010000000000 $
b111010000000000 '
0#
b1110100 *
#116200
1#
#116400
0#
#116600
1#
#116800
0#
#117000
b1110101 "
b1110101 &
b111010100000000 $
b111010100000000 '
1#
b1110101 *
#117200
0#
#117400
1#
#117600
0#
#117800
1#
#118000
b1110110 "
b1110110 &
b111011000000000 $
b111011000000000 '
0#
b1110110 *
#118200
1#
#118400
0#
#118600
1#
#118800
0#
#119000
b1110111 "
b1110111 &
b111011100000000 $
b111011100000000 '
1#
b1110111 *
#119200
0#
#119400
1#
#119600
0#
#119800
1#
#120000
b1111000 "
b1111000 &
b111100000000000 $
b111100000000000 '
0#
b1111000 *
#120200
1#
#120400
0#
#120600
1#
#120800
0#
#121000
b1111001 "
b1111001 &
b111100100000000 $
b111100100000000 '
1#
b1111001 *
#121200
0#
#121400
1#
#121600
0#
#121800
1#
#122000
b1111010 "
b1111010 &
b111101000000000 $
b111101000000000 '
0#
b1111010 *
#122200
1#
#122400
0#
#122600
1#
#122800
0#
#123000
b1111011 "
b1111011 &
b111101100000000 $
b111101100000000 '
1#
b1111011 *
#123200
0#
#123400
1#
#123600
0#
#123800
1#
#124000
b1111100 "
b1111100 &
b111110000000000 $
b111110000000000 '
0#
b1111100 *
#124200
1#
#124400
0#
#124600
1#
#124800
0#
#125000
b1111101 "
b1111101 &
b111110100000000 $
b111110100000000 '
1#
b1111101 *
#125200
0#
#125400
1#
#125600
0#
#125800
1#
#126000
b1111110 "
b1111110 &
b111111000000000 $
b111111000000000 '
0#
b1111110 *
#126200
1#
#126400
0#
#126600
1#
#126800
0#
#127000
bx !
bx (
1#
0%
b1111111 *
#127200
0#
#127400
1#
#127600
0#
#127800
1#
#128000
b0 !
b0 (
b0 "
b0 &
0#
b0 +
#128200
b0 )
1#
#128400
0#
#128600
1#
#128800
0#
#129000
b100000000 !
b100000000 (
b1 "
b1 &
1#
b1 +
#129200
0#
#129400
b100000000 )
1#
#129600
0#
#129800
1#
#130000
b1000000000 !
b1000000000 (
b10 "
b10 &
0#
b10 +
#130200
b1000000000 )
1#
#130400
0#
#130600
1#
#130800
0#
#131000
b1100000000 !
b1100000000 (
b11 "
b11 &
1#
b11 +
#131200
0#
#131400
b1100000000 )
1#
#131600
0#
#131800
1#
#132000
b10000000000 !
b10000000000 (
b100 "
b100 &
0#
b100 +
#132200
b10000000000 )
1#
#132400
0#
#132600
1#
#132800
0#
#133000
b10100000000 !
b10100000000 (
b101 "
b101 &
1#
b101 +
#133200
0#
#133400
b10100000000 )
1#
#133600
0#
#133800
1#
#134000
b11000000000 !
b11000000000 (
b110 "
b110 &
0#
b110 +
#134200
b11000000000 )
1#
#134400
0#
#134600
1#
#134800
0#
#135000
bx !
bx (
b111 "
b111 &
1#
b111 +
#135200
0#
#135400
bx )
1#
#135600
0#
#135800
1#
#136000
b1000 "
b1000 &
0#
b1000 +
#136200
1#
#136400
0#
#136600
1#
#136800
0#
#137000
b1001 "
b1001 &
1#
b1001 +
#137200
0#
#137400
1#
#137600
0#
#137800
1#
#138000
b1010 "
b1010 &
0#
b1010 +
#138200
1#
#138400
0#
#138600
1#
#138800
0#
#139000
b1011 "
b1011 &
1#
b1011 +
#139200
0#
#139400
1#
#139600
0#
#139800
1#
#140000
b1100 "
b1100 &
0#
b1100 +
#140200
1#
#140400
0#
#140600
1#
#140800
0#
#141000
b1101 "
b1101 &
1#
b1101 +
#141200
0#
#141400
1#
#141600
0#
#141800
1#
#142000
b1110 "
b1110 &
0#
b1110 +
#142200
1#
#142400
0#
#142600
1#
#142800
0#
#143000
b1111 "
b1111 &
1#
b1111 +
#143200
0#
#143400
1#
#143600
0#
#143800
1#
#144000
b10000 "
b10000 &
0#
b10000 +
#144200
1#
#144400
0#
#144600
1#
#144800
0#
#145000
b10001 "
b10001 &
1#
b10001 +
#145200
0#
#145400
1#
#145600
0#
#145800
1#
#146000
b10010 "
b10010 &
0#
b10010 +
#146200
1#
#146400
0#
#146600
1#
#146800
0#
#147000
b10011 "
b10011 &
1#
b10011 +
#147200
0#
#147400
1#
#147600
0#
#147800
1#
#148000
b10100 "
b10100 &
0#
b10100 +
#148200
1#
#148400
0#
#148600
1#
#148800
0#
#149000
b10101 "
b10101 &
1#
b10101 +
#149200
0#
#149400
1#
#149600
0#
#149800
1#
#150000
b10110 "
b10110 &
0#
b10110 +
#150200
1#
#150400
0#
#150600
1#
#150800
0#
#151000
b10111 "
b10111 &
1#
b10111 +
#151200
0#
#151400
1#
#151600
0#
#151800
1#
#152000
b11000 "
b11000 &
0#
b11000 +
#152200
1#
#152400
0#
#152600
1#
#152800
0#
#153000
b11001 "
b11001 &
1#
b11001 +
#153200
0#
#153400
1#
#153600
0#
#153800
1#
#154000
b11010 "
b11010 &
0#
b11010 +
#154200
1#
#154400
0#
#154600
1#
#154800
0#
#155000
b11011 "
b11011 &
1#
b11011 +
#155200
0#
#155400
1#
#155600
0#
#155800
1#
#156000
b11100 "
b11100 &
0#
b11100 +
#156200
1#
#156400
0#
#156600
1#
#156800
0#
#157000
b11101 "
b11101 &
1#
b11101 +
#157200
0#
#157400
1#
#157600
0#
#157800
1#
#158000
b11110 "
b11110 &
0#
b11110 +
#158200
1#
#158400
0#
#158600
1#
#158800
0#
#159000
b11111 "
b11111 &
1#
b11111 +
#159200
0#
#159400
1#
#159600
0#
#159800
1#
#160000
b100000 "
b100000 &
0#
b100000 +
#160200
1#
#160400
0#
#160600
1#
#160800
0#
#161000
b100001 "
b100001 &
1#
b100001 +
#161200
0#
#161400
1#
#161600
0#
#161800
1#
#162000
b100010 "
b100010 &
0#
b100010 +
#162200
1#
#162400
0#
#162600
1#
#162800
0#
#163000
b100011 "
b100011 &
1#
b100011 +
#163200
0#
#163400
1#
#163600
0#
#163800
1#
#164000
b100100 "
b100100 &
0#
b100100 +
#164200
1#
#164400
0#
#164600
1#
#164800
0#
#165000
b100101 "
b100101 &
1#
b100101 +
#165200
0#
#165400
1#
#165600
0#
#165800
1#
#166000
b100110 "
b100110 &
0#
b100110 +
#166200
1#
#166400
0#
#166600
1#
#166800
0#
#167000
b100111 "
b100111 &
1#
b100111 +
#167200
0#
#167400
1#
#167600
0#
#167800
1#
#168000
b101000 "
b101000 &
0#
b101000 +
#168200
1#
#168400
0#
#168600
1#
#168800
0#
#169000
b101001 "
b101001 &
1#
b101001 +
#169200
0#
#169400
1#
#169600
0#
#169800
1#
#170000
b101010 "
b101010 &
0#
b101010 +
#170200
1#
#170400
0#
#170600
1#
#170800
0#
#171000
b101011 "
b101011 &
1#
b101011 +
#171200
0#
#171400
1#
#171600
0#
#171800
1#
#172000
b101100 "
b101100 &
0#
b101100 +
#172200
1#
#172400
0#
#172600
1#
#172800
0#
#173000
b101101 "
b101101 &
1#
b101101 +
#173200
0#
#173400
1#
#173600
0#
#173800
1#
#174000
b101110 "
b101110 &
0#
b101110 +
#174200
1#
#174400
0#
#174600
1#
#174800
0#
#175000
b101111 "
b101111 &
1#
b101111 +
#175200
0#
#175400
1#
#175600
0#
#175800
1#
#176000
b110000 "
b110000 &
0#
b110000 +
#176200
1#
#176400
0#
#176600
1#
#176800
0#
#177000
b110001 "
b110001 &
1#
b110001 +
#177200
0#
#177400
1#
#177600
0#
#177800
1#
#178000
b110010 "
b110010 &
0#
b110010 +
#178200
1#
#178400
0#
#178600
1#
#178800
0#
#179000
b110011 "
b110011 &
1#
b110011 +
#179200
0#
#179400
1#
#179600
0#
#179800
1#
#180000
b110100 "
b110100 &
0#
b110100 +
#180200
1#
#180400
0#
#180600
1#
#180800
0#
#181000
b110101 "
b110101 &
1#
b110101 +
#181200
0#
#181400
1#
#181600
0#
#181800
1#
#182000
b110110 "
b110110 &
0#
b110110 +
#182200
1#
#182400
0#
#182600
1#
#182800
0#
#183000
b110111 "
b110111 &
1#
b110111 +
#183200
0#
#183400
1#
#183600
0#
#183800
1#
#184000
b111000 "
b111000 &
0#
b111000 +
#184200
1#
#184400
0#
#184600
1#
#184800
0#
#185000
b111001 "
b111001 &
1#
b111001 +
#185200
0#
#185400
1#
#185600
0#
#185800
1#
#186000
b111010 "
b111010 &
0#
b111010 +
#186200
1#
#186400
0#
#186600
1#
#186800
0#
#187000
b111011 "
b111011 &
1#
b111011 +
#187200
0#
#187400
1#
#187600
0#
#187800
1#
#188000
b111100 "
b111100 &
0#
b111100 +
#188200
1#
#188400
0#
#188600
1#
#188800
0#
#189000
b111101 "
b111101 &
1#
b111101 +
#189200
0#
#189400
1#
#189600
0#
#189800
1#
#190000
b111110 "
b111110 &
0#
b111110 +
#190200
1#
#190400
0#
#190600
1#
#190800
0#
#191000
b111111 "
b111111 &
1#
b111111 +
#191200
0#
#191400
1#
#191600
0#
#191800
1#
#192000
b1000000 "
b1000000 &
0#
b1000000 +
#192200
1#
#192400
0#
#192600
1#
#192800
0#
#193000
b1000001 "
b1000001 &
1#
b1000001 +
#193200
0#
#193400
1#
#193600
0#
#193800
1#
#194000
b1000010 "
b1000010 &
0#
b1000010 +
#194200
1#
#194400
0#
#194600
1#
#194800
0#
#195000
b1000011 "
b1000011 &
1#
b1000011 +
#195200
0#
#195400
1#
#195600
0#
#195800
1#
#196000
b1000100 "
b1000100 &
0#
b1000100 +
#196200
1#
#196400
0#
#196600
1#
#196800
0#
#197000
b1000101 "
b1000101 &
1#
b1000101 +
#197200
0#
#197400
1#
#197600
0#
#197800
1#
#198000
b1000110 "
b1000110 &
0#
b1000110 +
#198200
1#
#198400
0#
#198600
1#
#198800
0#
#199000
b1000111 "
b1000111 &
1#
b1000111 +
#199200
0#
#199400
1#
#199600
0#
#199800
1#
#200000
b1001000 "
b1001000 &
0#
b1001000 +
#200200
1#
#200400
0#
#200600
1#
#200800
0#
#201000
b1001001 "
b1001001 &
1#
b1001001 +
#201200
0#
#201400
1#
#201600
0#
#201800
1#
#202000
b1001010 "
b1001010 &
0#
b1001010 +
#202200
1#
#202400
0#
#202600
1#
#202800
0#
#203000
b1001011 "
b1001011 &
1#
b1001011 +
#203200
0#
#203400
1#
#203600
0#
#203800
1#
#204000
b1001100 "
b1001100 &
0#
b1001100 +
#204200
1#
#204400
0#
#204600
1#
#204800
0#
#205000
b1001101 "
b1001101 &
1#
b1001101 +
#205200
0#
#205400
1#
#205600
0#
#205800
1#
#206000
b1001110 "
b1001110 &
0#
b1001110 +
#206200
1#
#206400
0#
#206600
1#
#206800
0#
#207000
b1001111 "
b1001111 &
1#
b1001111 +
#207200
0#
#207400
1#
#207600
0#
#207800
1#
#208000
b1010000 "
b1010000 &
0#
b1010000 +
#208200
1#
